<?xml version="1.0" encoding="utf-8" ?>
<dwsync>
<file name="CredentialsProvider.php" server="10.244.88.40//opt/" local="133042819790000000" remote="133042819790000000" Dst="0" />
<file name="SigningConfigAWS.php" server="10.244.88.40//opt/" local="133042819790000000" remote="133042819790000000" Dst="0" />
<file name="SignedBodyHeaderType.php" server="10.244.88.40//opt/" local="133042819790000000" remote="133042819790000000" Dst="0" />
<file name="SigningResult.php" server="10.244.88.40//opt/" local="133042819790000000" remote="133042819790000000" Dst="0" />
<file name="Signing.php" server="10.244.88.40//opt/" local="133042819790000000" remote="133042819790000000" Dst="0" />
<file name="SignatureType.php" server="10.244.88.40//opt/" local="133042819790000000" remote="133042819790000000" Dst="0" />
<file name="StaticCredentialsProvider.php" server="10.244.88.40//opt/" local="133042819790000000" remote="133042819790000000" Dst="0" />
<file name="Signable.php" server="10.244.88.40//opt/" local="133042819790000000" remote="133042819790000000" Dst="0" />
<file name="AwsCredentials.php" server="10.244.88.40//opt/" local="133042819790000000" remote="133042819790000000" Dst="0" />
<file name="SigningAlgorithm.php" server="10.244.88.40//opt/" local="133042819790000000" remote="133042819790000000" Dst="0" />
</dwsync>