<?xml version="1.0" encoding="utf-8" ?>
<dwsync>
<file name="TaskAccessor.php" server="10.244.88.40//opt/" local="133042818430000000" remote="133042818430000000" Dst="0" />
<file name="Robo.php" server="10.244.88.40//opt/" local="133042818430000000" remote="133042818430000000" Dst="0" />
<file name="Result.php" server="10.244.88.40//opt/" local="133042818500000000" remote="133042818500000000" Dst="0" />
<file name="ResultData.php" server="10.244.88.40//opt/" local="133042818440000000" remote="133042818440000000" Dst="0" />
<file name="TaskInfo.php" server="10.244.88.40//opt/" local="133042818430000000" remote="133042818430000000" Dst="0" />
<file name="Config.php" server="10.244.88.40//opt/" local="133042818430000000" remote="133042818430000000" Dst="0" />
<file name="Tasks.php" server="10.244.88.40//opt/" local="133042818500000000" remote="133042818500000000" Dst="0" />
<file name="LoadAllTasks.php" server="10.244.88.40//opt/" local="133042818430000000" remote="133042818430000000" Dst="0" />
<file name="Application.php" server="10.244.88.40//opt/" local="133042818440000000" remote="133042818440000000" Dst="0" />
<file name="Runner.php" server="10.244.88.40//opt/" local="133042818440000000" remote="133042818440000000" Dst="0" />
<file name="GlobalOptionsEventListener.php" server="10.244.88.40//opt/" local="133042818430000000" remote="133042818430000000" Dst="0" />
</dwsync>